nr/__init__.py
nr/proxy/__init__.py
nr/proxy/py.typed
nr.proxy-1.1.1.dist-info/LICENSE.txt
nr.proxy-1.1.1.dist-info/METADATA
nr.proxy-1.1.1.dist-info/WHEEL
nr.proxy-1.1.1.dist-info/top_level.txt
nr.proxy-1.1.1.dist-info/RECORD
