Metadata-Version: 2.1
Name: nr.proxy
Version: 1.1.1
Summary: Provides proxy classes that allow accessing objects that are usually only accessible via function calls as objects directly.
Home-page: https://github.com/NiklasRosenstein/nr-python
Author: Niklas Rosenstein
Author-email: rosensteinniklas@gmail.com
License: MIT
Platform: UNKNOWN
Requires-Python: >=3.6.0,<4.0.0
Provides-Extra: test
Requires-Dist: pytest ; extra == 'test'
